    [{"id":"bitcoin","symbol":"btc","name":"Bitcoin","image":"https://assets.coingecko.com/coins/images/1/large/bitcoin.png?1547033579","current_price":26290,"market_cap":511795300923,"market_cap_rank":1,"fully_diluted_valuation":552269076558,"total_volume":34881033102,"high_24h":28411,"low_24h":25649,"price_change_24h":-2107.1095267852143,"price_change_percentage_24h":-7.42009,"market_cap_change_24h":-42112071769.24188,"market_cap_change_percentage_24h":-7.60273,"circulating_supply":19460987.0,"total_supply":21000000.0,"max_supply":21000000.0,"ath":69045,"ath_change_percentage":-61.94817,"ath_date":"2021-11-10T14:24:11.849Z","atl":67.81,"atl_change_percentage":38645.30151,"atl_date":"2013-07-06T00:00:00.000Z","roi":null,"last_updated":"2023-08-18T13:46:38.322Z"},{"id":"ethereum","symbol":"eth","name":"Ethereum","image":"https://assets.coingecko.com/coins/images/279/large/ethereum.png?1595348880","current_price":1680.09,"market_cap":201577397878,"market_cap_rank":2,"fully_diluted_valuation":201577397878,"total_volume":27057733533,"high_24h":1786.26,"low_24h":1576.13,"price_change_24h":-105.27013461548245,"price_change_percentage_24h":-5.89631,"market_cap_change_24h":-13370418135.471619,"market_cap_change_percentage_24h":-6.22031,"circulating_supply":120053867.802792,"total_supply":120053867.802792,"max_supply":null,"ath":4878.26,"ath_change_percentage":-65.6038,"ath_date":"2021-11-10T14:24:19.604Z","atl":0.432979,"atl_change_percentage":387433.04803,"atl_date":"2015-10-20T00:00:00.000Z","roi":{"times":84.47435049278504,"currency":"btc","percentage":8447.435049278503},"last_updated":"2023-08-18T13:46:41.007Z"},{"id":"tether","symbol":"usdt","name":"Tether","image":"https://assets.coingecko.com/coins/images/325/large/Tether.png?1668148663","current_price":0.999566,"market_cap":82726829067,"market_cap_rank":3,"fully_diluted_valuation":82726829067,"total_volume":29732741784,"high_24h":1.022,"low_24h":0.98644,"price_change_24h":0.00043217,"price_change_percentage_24h":0.04325,"market_cap_change_24h":-291811387.77926636,"market_cap_change_percentage_24h":-0.3515,"circulating_supply":82842337234.0993,"total_supply":82842337234.0993,"max_supply":null,"ath":1.32,"ath_change_percentage":-24.52504,"ath_date":"2018-07-24T00:00:00.000Z","atl":0.572521,"atl_change_percentage":74.42254,"atl_date":"2015-03-02T00:00:00.000Z","roi":null,"last_updated":"2023-08-18T13:45:03.546Z"},{"id":"binancecoin","symbol":"bnb","name":"BNB","image":"https://assets.coingecko.com/coins/images/825/large/bnb-icon2_2x.png?1644979850","current_price":218.14,"market_cap":33563328973,"market_cap_rank":4,"fully_diluted_valuation":43629492839,"total_volume":1110778648,"high_24h":230.48,"low_24h":212.27,"price_change_24h":-12.213947891594046,"price_change_percentage_24h":-5.3023,"market_cap_change_24h":-1925163154.9636078,"market_cap_change_percentage_24h":-5.42475,"circulating_supply":153856150.0,"total_supply":153856150.0,"max_supply":200000000.0,"ath":686.31,"ath_change_percentage":-68.22291,"ath_date":"2021-05-10T07:24:17.097Z","atl":0.0398177,"atl_change_percentage":547616.93881,"atl_date":"2017-10-19T00:00:00.000Z","roi":null,"last_updated":"2023-08-18T13:46:38.249Z"},{"id":"ripple","symbol":"xrp","name":"XRP","image":"https://assets.coingecko.com/coins/images/44/large/xrp-symbol-white-128.png?1605778731","current_price":0.503952,"market_cap":26636768725,"market_cap_rank":5,"fully_diluted_valuation":50408453577,"total_volume":2882607169,"high_24h":0.585542,"low_24h":0.47622,"price_change_24h":-0.08159011359598878,"price_change_percentage_24h":-13.93412,"market_cap_change_24h":-4373680366.1305275,"market_cap_change_percentage_24h":-14.10389,"circulating_supply":52841868447.0,"total_supply":99988501123.0,"max_supply":100000000000.0,"ath":3.4,"ath_change_percentage":-85.18631,"ath_date":"2018-01-07T00:00:00.000Z","atl":0.00268621,"atl_change_percentage":18641.51847,"atl_date":"2014-05-22T00:00:00.000Z","roi":null,"last_updated":"2023-08-18T13:46:40.514Z"},{"id":"usd-coin","symbol":"usdc","name":"USD Coin","image":"https://assets.coingecko.com/coins/images/6319/large/USD_Coin_icon.png?1547042389","current_price":0.999572,"market_cap":26190673729,"market_cap_rank":6,"fully_diluted_valuation":26196387830,"total_volume":14021594524,"high_24h":1.013,"low_24h":0.970334,"price_change_24h":-0.000221962764888284,"price_change_percentage_24h":-0.0222,"market_cap_change_24h":201816921,"market_cap_change_percentage_24h":0.77655,"circulating_supply":26212944719.8852,"total_supply":26218663679.1114,"max_supply":null,"ath":1.17,"ath_change_percentage":-14.75789,"ath_date":"2019-05-08T00:40:28.300Z","atl":0.877647,"atl_change_percentage":13.89999,"atl_date":"2023-03-11T08:02:13.981Z","roi":null,"last_updated":"2023-08-18T13:46:43.006Z"},{"id":"staked-ether","symbol":"steth","name":"Lido Staked Ether","image":"https://assets.coingecko.com/coins/images/13442/large/steth_logo.png?1608607546","current_price":1678.59,"market_cap":13708143085,"market_cap_rank":7,"fully_diluted_valuation":13708143085,"total_volume":30648736,"high_24h":1784.42,"low_24h":1576.31,"price_change_24h":-105.83211309429657,"price_change_percentage_24h":-5.93089,"market_cap_change_24h":-864873091.8302326,"market_cap_change_percentage_24h":-5.93476,"circulating_supply":8164748.49149879,"total_supply":8165458.31265321,"max_supply":8165458.31265321,"ath":4829.57,"ath_change_percentage":-65.34104,"ath_date":"2021-11-10T14:40:47.256Z","atl":482.9,"atl_change_percentage":246.63325,"atl_date":"2020-12-22T04:08:21.854Z","roi":null,"last_updated":"2023-08-18T13:46:45.025Z"},{"id":"cardano","symbol":"ada","name":"Cardano","image":"https://assets.coingecko.com/coins/images/975/large/cardano.png?1547034860","current_price":0.266416,"market_cap":9346842790,"market_cap_rank":8,"fully_diluted_valuation":12001931104,"total_volume":424963461,"high_24h":0.275549,"low_24h":0.246362,"price_change_24h":-0.009132813556792851,"price_change_percentage_24h":-3.31441,"market_cap_change_24h":-334288411.48781395,"market_cap_change_percentage_24h":-3.45299,"circulating_supply":35045020830.3234,"total_supply":45000000000.0,"max_supply":45000000000.0,"ath":3.09,"ath_change_percentage":-91.37051,"ath_date":"2021-09-02T06:00:10.474Z","atl":0.01925275,"atl_change_percentage":1283.61924,"atl_date":"2020-03-13T02:22:55.044Z","roi":null,"last_updated":"2023-08-18T13:46:39.899Z"},{"id":"solana","symbol":"sol","name":"Solana","image":"https://assets.coingecko.com/coins/images/4128/large/solana.png?1640133422","current_price":21.96,"market_cap":8944631545,"market_cap_rank":9,"fully_diluted_valuation":12192688094,"total_volume":694174933,"high_24h":23.26,"low_24h":20.89,"price_change_24h":-1.300939547113476,"price_change_percentage_24h":-5.59315,"market_cap_change_24h":-551926707.43746,"market_cap_change_percentage_24h":-5.81186,"circulating_supply":407363159.302796,"total_supply":555288601.59717,"max_supply":null,"ath":259.96,"ath_change_percentage":-91.58972,"ath_date":"2021-11-06T21:54:35.825Z","atl":0.500801,"atl_change_percentage":4265.66427,"atl_date":"2020-05-11T19:35:23.449Z","roi":null,"last_updated":"2023-08-18T13:46:37.983Z"},{"id":"dogecoin","symbol":"doge","name":"Dogecoin","image":"https://assets.coingecko.com/coins/images/5/large/dogecoin.png?1547792256","current_price":0.062831,"market_cap":8833782884,"market_cap_rank":10,"fully_diluted_valuation":8833804239,"total_volume":1037163070,"high_24h":0.067133,"low_24h":0.059074,"price_change_24h":-0.004301519264591395,"price_change_percentage_24h":-6.40748,"market_cap_change_24h":-627578542.470356,"market_cap_change_percentage_24h":-6.63307,"circulating_supply":140640406383.705,"total_supply":140640746383.705,"max_supply":null,"ath":0.731578,"ath_change_percentage":-91.42367,"ath_date":"2021-05-08T05:08:23.458Z","atl":8.69e-05,"atl_change_percentage":72097.74888,"atl_date":"2015-05-06T00:00:00.000Z","roi":null,"last_updated":"2023-08-18T13:46:42.742Z"},{"id":"tron","symbol":"trx","name":"TRON","image":"https://assets.coingecko.com/coins/images/1094/large/tron-logo.png?1547035066","current_price":0.073286,"market_cap":6553921145,"market_cap_rank":11,"fully_diluted_valuation":6553892756,"total_volume":354398908,"high_24h":0.075314,"low_24h":0.071496,"price_change_24h":-0.001815661199433563,"price_change_percentage_24h":-2.4176,"market_cap_change_24h":-165986131.85307693,"market_cap_change_percentage_24h":-2.47007,"circulating_supply":89436872433.639,"total_supply":89436485024.8215,"max_supply":null,"ath":0.231673,"ath_change_percentage":-68.37563,"ath_date":"2018-01-05T00:00:00.000Z","atl":0.00180434,"atl_change_percentage":3960.4871,"atl_date":"2017-11-12T00:00:00.000Z","roi":{"times":37.571653206157535,"currency":"usd","percentage":3757.165320615753},"last_updated":"2023-08-18T13:46:39.034Z"},{"id":"polkadot","symbol":"dot","name":"Polkadot","image":"https://assets.coingecko.com/coins/images/12171/large/polkadot.png?1639712644","current_price":4.51,"market_cap":5712762580,"market_cap_rank":12,"fully_diluted_valuation":6078157908,"total_volume":219744837,"high_24h":4.77,"low_24h":4.33,"price_change_24h":-0.2631817092834208,"price_change_percentage_24h":-5.51417,"market_cap_change_24h":-331922010.45983887,"market_cap_change_percentage_24h":-5.49114,"circulating_supply":1265596755.99904,"total_supply":1346545882.78115,"max_supply":null,"ath":54.98,"ath_change_percentage":-91.79738,"ath_date":"2021-11-04T14:10:09.301Z","atl":2.7,"atl_change_percentage":67.18993,"atl_date":"2020-08-20T05:48:11.359Z","roi":null,"last_updated":"2023-08-18T13:46:38.543Z"},{"id":"matic-network","symbol":"matic","name":"Polygon","image":"https://assets.coingecko.com/coins/images/4713/large/matic-token-icon.png?1624446912","current_price":0.576338,"market_cap":5368997646,"market_cap_rank":13,"fully_diluted_valuation":5761055277,"total_volume":439742820,"high_24h":0.608661,"low_24h":0.553695,"price_change_24h":-0.032323228486201394,"price_change_percentage_24h":-5.31055,"market_cap_change_24h":-317731322.9543562,"market_cap_change_percentage_24h":-5.58724,"circulating_supply":9319469069.28493,"total_supply":10000000000.0,"max_supply":10000000000.0,"ath":2.92,"ath_change_percentage":-80.25948,"ath_date":"2021-12-27T02:08:34.307Z","atl":0.00314376,"atl_change_percentage":18212.00601,"atl_date":"2019-05-10T00:00:00.000Z","roi":{"times":218.139862880412,"currency":"usd","percentage":21813.9862880412},"last_updated":"2023-08-18T13:46:37.244Z"},{"id":"shiba-inu","symbol":"shib","name":"Shiba Inu","image":"https://assets.coingecko.com/coins/images/11939/large/shiba.png?1622619446","current_price":8.62e-06,"market_cap":5058152966,"market_cap_rank":14,"fully_diluted_valuation":8582705476,"total_volume":495220123,"high_24h":8.82e-06,"low_24h":7.74e-06,"price_change_24h":-1.97077944522e-07,"price_change_percentage_24h":-2.23504,"market_cap_change_24h":-161998399.0757866,"market_cap_change_percentage_24h":-3.10333,"circulating_supply":589334143829605.5,"total_supply":999985848056796.0,"max_supply":null,"ath":8.616e-05,"ath_change_percentage":-90.12608,"ath_date":"2021-10-28T03:54:55.568Z","atl":5.6366e-11,"atl_change_percentage":15092672.69631,"atl_date":"2020-11-28T11:26:25.838Z","roi":null,"last_updated":"2023-08-18T13:46:41.369Z"},{"id":"litecoin","symbol":"ltc","name":"Litecoin","image":"https://assets.coingecko.com/coins/images/2/large/litecoin.png?1547033580","current_price":64.96,"market_cap":4778126568,"market_cap_rank":15,"fully_diluted_valuation":5456658237,"total_volume":1534922390,"high_24h":75.34,"low_24h":61.43,"price_change_24h":-10.377439022803841,"price_change_percentage_24h":-13.775,"market_cap_change_24h":-773164681.8119326,"market_cap_change_percentage_24h":-13.92765,"circulating_supply":73554658.2334713,"total_supply":84000000.0,"max_supply":84000000.0,"ath":410.26,"ath_change_percentage":-84.17547,"ath_date":"2021-05-10T03:13:07.904Z","atl":1.15,"atl_change_percentage":5551.05336,"atl_date":"2015-01-14T00:00:00.000Z","roi":null,"last_updated":"2023-08-18T13:46:44.528Z"},{"id":"the-open-network","symbol":"ton","name":"Toncoin","image":"https://assets.coingecko.com/coins/images/17980/large/ton_symbol.png?1670498136","current_price":1.35,"market_cap":4629043256,"market_cap_rank":16,"fully_diluted_valuation":6854683490,"total_volume":22720656,"high_24h":1.42,"low_24h":1.29,"price_change_24h":-0.06386224397720563,"price_change_percentage_24h":-4.52902,"market_cap_change_24h":-232964866.57857227,"market_cap_change_percentage_24h":-4.79154,"circulating_supply":3438749070.024,"total_supply":5092096826.57858,"max_supply":null,"ath":5.29,"ath_change_percentage":-74.60649,"ath_date":"2021-11-12T06:50:02.476Z","atl":0.519364,"atl_change_percentage":158.68547,"atl_date":"2021-09-21T00:33:11.092Z","roi":null,"last_updated":"2023-08-18T13:46:44.949Z"},{"id":"wrapped-bitcoin","symbol":"wbtc","name":"Wrapped Bitcoin","image":"https://assets.coingecko.com/coins/images/7598/large/wrapped_bitcoin_wbtc.png?1548822744","current_price":26358,"market_cap":4278656261,"market_cap_rank":17,"fully_diluted_valuation":4278656261,"total_volume":251734424,"high_24h":28425,"low_24h":25727,"price_change_24h":-2066.835895522472,"price_change_percentage_24h":-7.27123,"market_cap_change_24h":-343955731.42320347,"market_cap_change_percentage_24h":-7.44072,"circulating_supply":162305.25767567,"total_supply":162305.25767567,"max_supply":162305.25767567,"ath":70643,"ath_change_percentage":-62.72027,"ath_date":"2021-11-10T14:40:19.650Z","atl":3139.17,"atl_change_percentage":738.9364,"atl_date":"2019-04-02T00:00:00.000Z","roi":null,"last_updated":"2023-08-18T13:46:38.409Z"},{"id":"dai","symbol":"dai","name":"Dai","image":"https://assets.coingecko.com/coins/images/9956/large/Badge_Dai.png?1687143508","current_price":0.998724,"market_cap":3940745131,"market_cap_rank":18,"fully_diluted_valuation":3940745131,"total_volume":263427400,"high_24h":1.005,"low_24h":0.995639,"price_change_24h":-0.001679813848643685,"price_change_percentage_24h":-0.16791,"market_cap_change_24h":33694525,"market_cap_change_percentage_24h":0.8624,"circulating_supply":3943871044.40585,"total_supply":3943871044.40585,"max_supply":null,"ath":1.22,"ath_change_percentage":-18.04333,"ath_date":"2020-03-13T03:02:50.373Z","atl":0.88196,"atl_change_percentage":13.26987,"atl_date":"2023-03-11T07:50:50.514Z","roi":null,"last_updated":"2023-08-18T13:45:03.372Z"},{"id":"uniswap","symbol":"uni","name":"Uniswap","image":"https://assets.coingecko.com/coins/images/12504/large/uni.jpg?1687143398","current_price":4.98,"market_cap":3755969272,"market_cap_rank":19,"fully_diluted_valuation":4982933627,"total_volume":219742129,"high_24h":5.41,"low_24h":4.81,"price_change_24h":-0.4313554591965305,"price_change_percentage_24h":-7.97105,"market_cap_change_24h":-318018608.16557693,"market_cap_change_percentage_24h":-7.80608,"circulating_supply":753766667.0,"total_supply":1000000000.0,"max_supply":1000000000.0,"ath":44.92,"ath_change_percentage":-88.94984,"ath_date":"2021-05-03T05:25:04.822Z","atl":1.03,"atl_change_percentage":381.81477,"atl_date":"2020-09-17T01:20:38.214Z","roi":null,"last_updated":"2023-08-18T13:46:42.998Z"},{"id":"avalanche-2","symbol":"avax","name":"Avalanche","image":"https://assets.coingecko.com/coins/images/12559/large/Avalanche_Circle_RedWhite_Trans.png?1670992574","current_price":10.84,"market_cap":3728492589,"market_cap_rank":20,"fully_diluted_valuation":7803967196,"total_volume":193553862,"high_24h":11.4,"low_24h":10.37,"price_change_24h":-0.5567764505773578,"price_change_percentage_24h":-4.88394,"market_cap_change_24h":-204031649.3796649,"market_cap_change_percentage_24h":-5.18831,"circulating_supply":343993586.446865,"total_supply":430713025.528297,"max_supply":720000000.0,"ath":144.96,"ath_change_percentage":-92.54604,"ath_date":"2021-11-21T14:18:56.538Z","atl":2.8,"atl_change_percentage":285.75897,"atl_date":"2020-12-31T13:15:21.540Z","roi":null,"last_updated":"2023-08-18T13:46:40.062Z"},{"id":"leo-token","symbol":"leo","name":"LEO Token","image":"https://assets.coingecko.com/coins/images/8418/large/leo-token.png?1558326215","current_price":3.96,"market_cap":3664879598,"market_cap_rank":21,"fully_diluted_valuation":3884307685,"total_volume":500889,"high_24h":4.01,"low_24h":3.87,"price_change_24h":-0.03725036730169817,"price_change_percentage_24h":-0.93288,"market_cap_change_24h":-45858731.98954344,"market_cap_change_percentage_24h":-1.23584,"circulating_supply":929582424.9,"total_supply":985239504.0,"max_supply":null,"ath":8.14,"ath_change_percentage":-51.51914,"ath_date":"2022-02-08T17:40:10.285Z","atl":0.799859,"atl_change_percentage":393.09733,"atl_date":"2019-12-24T15:14:35.376Z","roi":null,"last_updated":"2023-08-18T13:46:42.958Z"},{"id":"bitcoin-cash","symbol":"bch","name":"Bitcoin Cash","image":"https://assets.coingecko.com/coins/images/780/large/bitcoin-cash-circle.png?1594689492","current_price":185.18,"market_cap":3611907180,"market_cap_rank":22,"fully_diluted_valuation":3893864725,"total_volume":386722108,"high_24h":207.28,"low_24h":177.13,"price_change_24h":-22.102186910418027,"price_change_percentage_24h":-10.66305,"market_cap_change_24h":-436102949.08278036,"market_cap_change_percentage_24h":-10.77327,"circulating_supply":19479374.8966508,"total_supply":21000000.0,"max_supply":21000000.0,"ath":3785.82,"ath_change_percentage":-95.11439,"ath_date":"2017-12-20T00:00:00.000Z","atl":76.93,"atl_change_percentage":140.41172,"atl_date":"2018-12-16T00:00:00.000Z","roi":null,"last_updated":"2023-08-18T13:46:37.895Z"},{"id":"chainlink","symbol":"link","name":"Chainlink","image":"https://assets.coingecko.com/coins/images/877/large/chainlink-new-logo.png?1547034700","current_price":6.23,"market_cap":3355868087,"market_cap_rank":23,"fully_diluted_valuation":6236514153,"total_volume":513793277,"high_24h":6.79,"low_24h":5.93,"price_change_24h":-0.5572786233707072,"price_change_percentage_24h":-8.20472,"market_cap_change_24h":-307023297.6091342,"market_cap_change_percentage_24h":-8.38199,"circulating_supply":538099971.2305644,"total_supply":1000000000.0,"max_supply":1000000000.0,"ath":52.7,"ath_change_percentage":-88.17822,"ath_date":"2021-05-10T00:13:57.214Z","atl":0.148183,"atl_change_percentage":4104.03606,"atl_date":"2017-11-29T00:00:00.000Z","roi":null,"last_updated":"2023-08-18T13:46:38.531Z"},{"id":"binance-usd","symbol":"busd","name":"Binance USD","image":"https://assets.coingecko.com/coins/images/9576/large/BUSD.png?1568947766","current_price":1.002,"market_cap":3279565619,"market_cap_rank":24,"fully_diluted_valuation":3279565619,"total_volume":7050733894,"high_24h":1.018,"low_24h":0.941186,"price_change_24h":0.0019924,"price_change_percentage_24h":0.19927,"market_cap_change_24h":-27255034.37319565,"market_cap_change_percentage_24h":-0.82421,"circulating_supply":3278535261.67,"total_supply":3278535261.67,"max_supply":null,"ath":1.15,"ath_change_percentage":-13.4883,"ath_date":"2020-03-13T02:35:42.953Z","atl":0.901127,"atl_change_percentage":10.80805,"atl_date":"2021-05-19T13:04:37.445Z","roi":null,"last_updated":"2023-08-18T13:46:46.027Z"},{"id":"stellar","symbol":"xlm","name":"Stellar","image":"https://assets.coingecko.com/coins/images/100/large/Stellar_symbol_black_RGB.png?1552356157","current_price":0.116513,"market_cap":3187836874,"market_cap_rank":25,"fully_diluted_valuation":5824735311,"total_volume":156364126,"high_24h":0.125449,"low_24h":0.110932,"price_change_24h":-0.008936010954548991,"price_change_percentage_24h":-7.12324,"market_cap_change_24h":-261832711.5761652,"market_cap_change_percentage_24h":-7.59008,"circulating_supply":27365628243.2191,"total_supply":50001787244.4735,"max_supply":50001787244.4735,"ath":0.875563,"ath_change_percentage":-86.69771,"ath_date":"2018-01-03T00:00:00.000Z","atl":0.00047612,"atl_change_percentage":24362.12413,"atl_date":"2015-03-05T00:00:00.000Z","roi":null,"last_updated":"2023-08-18T13:46:37.962Z"},{"id":"true-usd","symbol":"tusd","name":"TrueUSD","image":"https://assets.coingecko.com/coins/images/3449/large/tusd.png?1618395665","current_price":0.999158,"market_cap":2761671694,"market_cap_rank":26,"fully_diluted_valuation":2761671694,"total_volume":4112489656,"high_24h":1.017,"low_24h":0.939121,"price_change_24h":0.00181252,"price_change_percentage_24h":0.18173,"market_cap_change_24h":11523498,"market_cap_change_percentage_24h":0.41901,"circulating_supply":2763471415.06,"total_supply":2763471415.06,"max_supply":null,"ath":1.62,"ath_change_percentage":-38.3069,"ath_date":"2018-08-26T20:41:09.375Z","atl":0.88355,"atl_change_percentage":13.01125,"atl_date":"2020-03-12T10:47:51.380Z","roi":null,"last_updated":"2023-08-18T13:46:37.809Z"},{"id":"monero","symbol":"xmr","name":"Monero","image":"https://assets.coingecko.com/coins/images/69/large/monero_logo.png?1547033729","current_price":144.02,"market_cap":2614332763,"market_cap_rank":27,"fully_diluted_valuation":null,"total_volume":94408823,"high_24h":152.18,"low_24h":139.55,"price_change_24h":-8.157367230071173,"price_change_percentage_24h":-5.36033,"market_cap_change_24h":-147542124.26697254,"market_cap_change_percentage_24h":-5.3421,"circulating_supply":18147820.3764146,"total_supply":null,"max_supply":null,"ath":542.33,"ath_change_percentage":-73.4575,"ath_date":"2018-01-09T00:00:00.000Z","atl":0.216177,"atl_change_percentage":66487.56392,"atl_date":"2015-01-14T00:00:00.000Z","roi":null,"last_updated":"2023-08-18T13:46:46.924Z"},{"id":"okb","symbol":"okb","name":"OKB","image":"https://assets.coingecko.com/coins/images/4463/large/WeChat_Image_20220118095654.png?1642471050","current_price":42.21,"market_cap":2532943780,"market_cap_rank":28,"fully_diluted_valuation":12664718902,"total_volume":8598392,"high_24h":44.81,"low_24h":40.56,"price_change_24h":-2.549249763747177,"price_change_percentage_24h":-5.69514,"market_cap_change_24h":-156481726.4214325,"market_cap_change_percentage_24h":-5.81841,"circulating_supply":60000000.0,"total_supply":235957685.3,"max_supply":300000000.0,"ath":58.66,"ath_change_percentage":-28.08392,"ath_date":"2023-02-18T01:21:37.582Z","atl":0.580608,"atl_change_percentage":7165.65677,"atl_date":"2019-01-14T00:00:00.000Z","roi":null,"last_updated":"2023-08-18T13:46:42.413Z"},{"id":"ethereum-classic","symbol":"etc","name":"Ethereum Classic","image":"https://assets.coingecko.com/coins/images/453/large/ethereum-classic-logo.png?1547034169","current_price":15.7,"market_cap":2235674792,"market_cap_rank":29,"fully_diluted_valuation":3304543576,"total_volume":191366259,"high_24h":16.29,"low_24h":14.51,"price_change_24h":-0.5977553133239244,"price_change_percentage_24h":-3.66863,"market_cap_change_24h":-93810656.43846655,"market_cap_change_percentage_24h":-4.0271,"circulating_supply":142548181.844497,"total_supply":210700000.0,"max_supply":210700000.0,"ath":167.09,"ath_change_percentage":-90.61749,"ath_date":"2021-05-06T18:34:22.133Z","atl":0.615038,"atl_change_percentage":2448.9168,"atl_date":"2016-07-25T00:00:00.000Z","roi":{"times":33.879831110546775,"currency":"usd","percentage":3387.983111054678},"last_updated":"2023-08-18T13:46:43.767Z"},{"id":"cosmos","symbol":"atom","name":"Cosmos Hub","image":"https://assets.coingecko.com/coins/images/1481/large/cosmos_hub.png?1555657960","current_price":7.47,"market_cap":2184963201,"market_cap_rank":30,"fully_diluted_valuation":null,"total_volume":263795014,"high_24h":8.11,"low_24h":7.38,"price_change_24h":-0.491379384183106,"price_change_percentage_24h":-6.17466,"market_cap_change_24h":-152833673.0839448,"market_cap_change_percentage_24h":-6.53751,"circulating_supply":292586163.827428,"total_supply":null,"max_supply":null,"ath":44.45,"ath_change_percentage":-83.21653,"ath_date":"2022-01-17T00:34:41.497Z","atl":1.16,"atl_change_percentage":543.06393,"atl_date":"2020-03-13T02:27:44.591Z","roi":{"times":73.66620450345495,"currency":"usd","percentage":7366.620450345495},"last_updated":"2023-08-18T13:46:44.283Z"},{"id":"hedera-hashgraph","symbol":"hbar","name":"Hedera","image":"https://assets.coingecko.com/coins/images/3688/large/hbar.png?1637045634","current_price":0.057108,"market_cap":1884337445,"market_cap_rank":31,"fully_diluted_valuation":2856456840,"total_volume":93264605,"high_24h":0.062232,"low_24h":0.054672,"price_change_24h":-0.003685917844010775,"price_change_percentage_24h":-6.06295,"market_cap_change_24h":-129215161.6819117,"market_cap_change_percentage_24h":-6.41727,"circulating_supply":32983824902.0102,"total_supply":50000000000.0,"max_supply":50000000000.0,"ath":0.569229,"ath_change_percentage":-89.97463,"ath_date":"2021-09-15T10:40:28.318Z","atl":0.00986111,"atl_change_percentage":478.71075,"atl_date":"2020-01-02T17:30:24.852Z","roi":null,"last_updated":"2023-08-18T13:46:38.931Z"},{"id":"filecoin","symbol":"fil","name":"Filecoin","image":"https://assets.coingecko.com/coins/images/12817/large/filecoin.png?1602753933","current_price":3.51,"market_cap":1553878982,"market_cap_rank":32,"fully_diluted_valuation":6883143117,"total_volume":164769609,"high_24h":3.77,"low_24h":3.23,"price_change_24h":-0.26190436782935134,"price_change_percentage_24h":-6.95063,"market_cap_change_24h":-118778401.36526942,"market_cap_change_percentage_24h":-7.10118,"circulating_supply":442820978.0,"total_supply":1961541752.0,"max_supply":1961541752.0,"ath":236.84,"ath_change_percentage":-98.52414,"ath_date":"2021-04-01T13:29:41.564Z","atl":2.64,"atl_change_percentage":32.35402,"atl_date":"2022-12-16T22:45:28.552Z","roi":null,"last_updated":"2023-08-18T13:46:37.624Z"},{"id":"internet-computer","symbol":"icp","name":"Internet Computer","image":"https://assets.coingecko.com/coins/images/14495/large/Internet_Computer_logo.png?1620703073","current_price":3.52,"market_cap":1550464018,"market_cap_rank":33,"fully_diluted_valuation":1647335868,"total_volume":51012393,"high_24h":3.75,"low_24h":3.32,"price_change_24h":-0.2320022327771447,"price_change_percentage_24h":-6.18682,"market_cap_change_24h":-106788429.63911414,"market_cap_change_percentage_24h":-6.4437,"circulating_supply":441621522.547921,"total_supply":503920595.418696,"max_supply":469213710.0,"ath":700.65,"ath_change_percentage":-99.50112,"ath_date":"2021-05-10T16:05:53.653Z","atl":3.32,"atl_change_percentage":5.15592,"atl_date":"2023-08-17T21:50:26.760Z","roi":null,"last_updated":"2023-08-18T13:46:39.331Z"},{"id":"lido-dao","symbol":"ldo","name":"Lido DAO","image":"https://assets.coingecko.com/coins/images/13573/large/Lido_DAO.png?1609873644","current_price":1.65,"market_cap":1452372256,"market_cap_rank":34,"fully_diluted_valuation":1652587982,"total_volume":102501000,"high_24h":1.72,"low_24h":1.5,"price_change_24h":-0.0635513064341604,"price_change_percentage_24h":-3.70466,"market_cap_change_24h":-61972026.548951626,"market_cap_change_percentage_24h":-4.09233,"circulating_supply":878847161.025269,"total_supply":1000000000.0,"max_supply":1000000000.0,"ath":7.3,"ath_change_percentage":-77.49739,"ath_date":"2021-08-20T08:35:20.158Z","atl":0.40615,"atl_change_percentage":304.61351,"atl_date":"2022-06-18T20:55:12.035Z","roi":null,"last_updated":"2023-08-18T13:46:44.482Z"},{"id":"quant-network","symbol":"qnt","name":"Quant","image":"https://assets.coingecko.com/coins/images/3370/large/5ZOu7brX_400x400.jpg?1612437252","current_price":99.52,"market_cap":1446566555,"market_cap_rank":35,"fully_diluted_valuation":1453361360,"total_volume":34689947,"high_24h":100.43,"low_24h":90.75,"price_change_24h":-0.6869626779819242,"price_change_percentage_24h":-0.68558,"market_cap_change_24h":-12274642.761298895,"market_cap_change_percentage_24h":-0.8414,"circulating_supply":14544176.164091088,"total_supply":14612493.0,"max_supply":14612493.0,"ath":427.42,"ath_change_percentage":-76.72853,"ath_date":"2021-09-11T09:15:00.668Z","atl":0.215773,"atl_change_percentage":45998.14129,"atl_date":"2018-08-23T00:00:00.000Z","roi":{"times":24.475198621934243,"currency":"eth","percentage":2447.5198621934246},"last_updated":"2023-08-18T13:46:42.369Z"},{"id":"mantle","symbol":"mnt","name":"Mantle","image":"https://assets.coingecko.com/coins/images/30980/large/token-logo.png?1689320029","current_price":0.428742,"market_cap":1386627564,"market_cap_rank":36,"fully_diluted_valuation":2666407122,"total_volume":22401097,"high_24h":0.447913,"low_24h":0.42587,"price_change_24h":-0.016983818653591557,"price_change_percentage_24h":-3.81037,"market_cap_change_24h":-56721382.01756954,"market_cap_change_percentage_24h":-3.92985,"circulating_supply":3234268324.76314,"total_supply":6219316794.99,"max_supply":6219316794.99,"ath":0.600075,"ath_change_percentage":-28.55405,"ath_date":"2023-07-20T22:39:30.228Z","atl":0.42587,"atl_change_percentage":0.67125,"atl_date":"2023-08-17T21:50:22.808Z","roi":null,"last_updated":"2023-08-18T13:46:39.030Z"},{"id":"crypto-com-chain","symbol":"cro","name":"Cronos","image":"https://assets.coingecko.com/coins/images/7310/large/cro_token_logo.png?1669699773","current_price":0.052008,"market_cap":1364658972,"market_cap_rank":37,"fully_diluted_valuation":1561367403,"total_volume":12214564,"high_24h":0.054293,"low_24h":0.051205,"price_change_24h":-0.002285355665479265,"price_change_percentage_24h":-4.20926,"market_cap_change_24h":-60991602.478725195,"market_cap_change_percentage_24h":-4.27816,"circulating_supply":26220458481.0716,"total_supply":30000000000.0,"max_supply":null,"ath":0.965407,"ath_change_percentage":-94.62019,"ath_date":"2021-11-24T15:53:54.855Z","atl":0.0121196,"atl_change_percentage":328.53756,"atl_date":"2019-02-08T00:00:00.000Z","roi":null,"last_updated":"2023-08-18T13:46:34.219Z"},{"id":"aptos","symbol":"apt","name":"Aptos","image":"https://assets.coingecko.com/coins/images/26455/large/aptos_round.png?1666839629","current_price":5.79,"market_cap":1308735264,"market_cap_rank":38,"fully_diluted_valuation":6084908336,"total_volume":158392472,"high_24h":6.28,"low_24h":5.5,"price_change_24h":-0.4727163578629767,"price_change_percentage_24h":-7.54422,"market_cap_change_24h":-109648188.52480173,"market_cap_change_percentage_24h":-7.7305,"circulating_supply":225941897.280493,"total_supply":1050507113.53302,"max_supply":null,"ath":19.92,"ath_change_percentage":-70.94078,"ath_date":"2023-01-26T14:25:17.390Z","atl":3.08,"atl_change_percentage":87.95768,"atl_date":"2022-12-29T21:35:14.796Z","roi":null,"last_updated":"2023-08-18T13:46:42.765Z"},{"id":"arbitrum","symbol":"arb","name":"Arbitrum","image":"https://assets.coingecko.com/coins/images/16547/large/photo_2023-03-29_21.47.00.jpeg?1680097630","current_price":1.01,"market_cap":1286767367,"market_cap_rank":39,"fully_diluted_valuation":10092293078,"total_volume":304290966,"high_24h":1.044,"low_24h":0.940354,"price_change_24h":-0.03378480643100379,"price_change_percentage_24h":-3.23734,"market_cap_change_24h":-47424789.194095135,"market_cap_change_percentage_24h":-3.55457,"circulating_supply":1275000000.0,"total_supply":10000000000.0,"max_supply":10000000000.0,"ath":8.67,"ath_change_percentage":-88.39201,"ath_date":"2023-03-23T13:10:03.106Z","atl":0.912886,"atl_change_percentage":10.28668,"atl_date":"2023-06-15T07:25:14.752Z","roi":null,"last_updated":"2023-08-18T13:46:38.128Z"},{"id":"vechain","symbol":"vet","name":"VeChain","image":"https://assets.coingecko.com/coins/images/1167/large/VET_Token_Icon.png?1680067517","current_price":0.0160228,"market_cap":1164784691,"market_cap_rank":40,"fully_diluted_valuation":1389014925,"total_volume":66072318,"high_24h":0.0167486,"low_24h":0.01527536,"price_change_24h":-0.000725798014445108,"price_change_percentage_24h":-4.33348,"market_cap_change_24h":-58049381.09354472,"market_cap_change_percentage_24h":-4.74712,"circulating_supply":72714516834.0,"total_supply":85985041177.0,"max_supply":86712634466.0,"ath":0.280991,"ath_change_percentage":-94.30249,"ath_date":"2021-04-19T01:08:21.675Z","atl":0.00191713,"atl_change_percentage":735.07463,"atl_date":"2020-03-13T02:29:59.652Z","roi":{"times":2.338618630041818,"currency":"eth","percentage":233.86186300418183},"last_updated":"2023-08-18T13:46:38.178Z"},{"id":"near","symbol":"near","name":"NEAR Protocol","image":"https://assets.coingecko.com/coins/images/10365/large/near.jpg?1683515160","current_price":1.15,"market_cap":1078343412,"market_cap_rank":41,"fully_diluted_valuation":1145137548,"total_volume":122165912,"high_24h":1.21,"low_24h":1.083,"price_change_24h":-0.06700389391840655,"price_change_percentage_24h":-5.52482,"market_cap_change_24h":-66263343.16480732,"market_cap_change_percentage_24h":-5.78918,"circulating_supply":941671517.686093,"total_supply":1000000000.0,"max_supply":null,"ath":20.44,"ath_change_percentage":-94.4229,"ath_date":"2022-01-16T22:09:45.873Z","atl":0.526762,"atl_change_percentage":116.38889,"atl_date":"2020-11-04T16:09:15.137Z","roi":null,"last_updated":"2023-08-18T13:46:38.242Z"},{"id":"optimism","symbol":"op","name":"Optimism","image":"https://assets.coingecko.com/coins/images/25244/large/Optimism.png?1660904599","current_price":1.42,"market_cap":1018610171,"market_cap_rank":42,"fully_diluted_valuation":6104148184,"total_volume":230668971,"high_24h":1.45,"low_24h":1.29,"price_change_24h":-0.011645780652419724,"price_change_percentage_24h":-0.81166,"market_cap_change_24h":-12668570.00870037,"market_cap_change_percentage_24h":-1.22843,"circulating_supply":716708907.0,"total_supply":4294967296.0,"max_supply":4294967296.0,"ath":3.22,"ath_change_percentage":-55.92527,"ath_date":"2023-02-24T20:20:00.509Z","atl":0.402159,"atl_change_percentage":253.2461,"atl_date":"2022-06-18T20:54:52.178Z","roi":null,"last_updated":"2023-08-18T13:46:45.711Z"},{"id":"maker","symbol":"mkr","name":"Maker","image":"https://assets.coingecko.com/coins/images/1364/large/Mark_Maker.png?1585191826","current_price":1096.91,"market_cap":988791013,"market_cap_rank":43,"fully_diluted_valuation":1103176993,"total_volume":141948197,"high_24h":1144.85,"low_24h":1025.66,"price_change_24h":-47.9411914843065,"price_change_percentage_24h":-4.18754,"market_cap_change_24h":-45457808.63738179,"market_cap_change_percentage_24h":-4.39525,"circulating_supply":901310.9472893132,"total_supply":977631.036950888,"max_supply":1005577.0,"ath":6292.31,"ath_change_percentage":-82.58978,"ath_date":"2021-05-03T21:54:29.333Z","atl":168.36,"atl_change_percentage":550.70169,"atl_date":"2020-03-16T20:52:36.527Z","roi":null,"last_updated":"2023-08-18T13:46:45.214Z"},{"id":"rocket-pool-eth","symbol":"reth","name":"Rocket Pool ETH","image":"https://assets.coingecko.com/coins/images/20764/large/reth.png?1637652366","current_price":1835.37,"market_cap":916858156,"market_cap_rank":44,"fully_diluted_valuation":917092981,"total_volume":27926540,"high_24h":1941.79,"low_24h":1734.38,"price_change_24h":-106.42249465113969,"price_change_percentage_24h":-5.48063,"market_cap_change_24h":-53726516.55896819,"market_cap_change_percentage_24h":-5.53548,"circulating_supply":499212.030885811,"total_supply":499339.888800516,"max_supply":null,"ath":4814.31,"ath_change_percentage":-61.94197,"ath_date":"2021-12-01T08:03:50.749Z","atl":887.26,"atl_change_percentage":106.50367,"atl_date":"2022-06-18T20:55:45.957Z","roi":null,"last_updated":"2023-08-18T13:46:40.501Z"},{"id":"xdce-crowd-sale","symbol":"xdc","name":"XDC Network","image":"https://assets.coingecko.com/coins/images/2912/large/xdc-icon.png?1633700890","current_price":0.059526,"market_cap":825989443,"market_cap_rank":45,"fully_diluted_valuation":2256583132,"total_volume":13304042,"high_24h":0.059741,"low_24h":0.054768,"price_change_24h":0.00065106,"price_change_percentage_24h":1.10584,"market_cap_change_24h":6438412,"market_cap_change_percentage_24h":0.7856,"circulating_supply":13857010049.25,"total_supply":37857015510.45,"max_supply":null,"ath":0.192754,"ath_change_percentage":-69.05944,"ath_date":"2021-08-21T04:39:48.324Z","atl":0.00039532,"atl_change_percentage":14986.38455,"atl_date":"2019-07-22T00:00:00.000Z","roi":{"times":3.7124944250187326,"currency":"eth","percentage":371.24944250187326},"last_updated":"2023-08-18T13:46:44.348Z"},{"id":"the-graph","symbol":"grt","name":"The Graph","image":"https://assets.coingecko.com/coins/images/13397/large/Graph_Token.png?1608145566","current_price":0.089939,"market_cap":821722835,"market_cap_rank":46,"fully_diluted_valuation":899990243,"total_volume":64402280,"high_24h":0.098126,"low_24h":0.085717,"price_change_24h":-0.008145722108144737,"price_change_percentage_24h":-8.30476,"market_cap_change_24h":-76591691.47202575,"market_cap_change_percentage_24h":-8.52616,"circulating_supply":9130352712.69541,"total_supply":10000000000.0,"max_supply":null,"ath":2.84,"ath_change_percentage":-96.85311,"ath_date":"2021-02-12T07:28:45.775Z","atl":0.052051,"atl_change_percentage":71.79138,"atl_date":"2022-11-22T10:05:03.503Z","roi":null,"last_updated":"2023-08-18T13:46:39.422Z"},{"id":"aave","symbol":"aave","name":"Aave","image":"https://assets.coingecko.com/coins/images/12645/large/AAVE.png?1601374110","current_price":56.25,"market_cap":810734145,"market_cap_rank":47,"fully_diluted_valuation":893363699,"total_volume":118873997,"high_24h":59.93,"low_24h":52.99,"price_change_24h":-3.6809928678141617,"price_change_percentage_24h":-6.1418,"market_cap_change_24h":-60630379.65270376,"market_cap_change_percentage_24h":-6.9581,"circulating_supply":14520117.993054658,"total_supply":16000000.0,"max_supply":16000000.0,"ath":661.69,"ath_change_percentage":-91.56022,"ath_date":"2021-05-18T21:19:59.514Z","atl":26.02,"atl_change_percentage":114.59822,"atl_date":"2020-11-05T09:20:11.928Z","roi":null,"last_updated":"2023-08-18T13:46:42.224Z"},{"id":"frax","symbol":"frax","name":"Frax","image":"https://assets.coingecko.com/coins/images/13422/large/FRAX_icon.png?1679886922","current_price":0.997435,"market_cap":804652067,"market_cap_rank":48,"fully_diluted_valuation":804652067,"total_volume":24230709,"high_24h":1.005,"low_24h":0.991483,"price_change_24h":-0.002099302608314036,"price_change_percentage_24h":-0.21003,"market_cap_change_24h":-863806.6328628063,"market_cap_change_percentage_24h":-0.10724,"circulating_supply":806724580.559441,"total_supply":806724580.559441,"max_supply":null,"ath":1.14,"ath_change_percentage":-12.69716,"ath_date":"2021-02-07T12:55:35.766Z","atl":0.874536,"atl_change_percentage":13.84847,"atl_date":"2023-03-11T07:50:39.316Z","roi":null,"last_updated":"2023-08-18T13:46:41.383Z"},{"id":"whitebit","symbol":"wbt","name":"WhiteBIT Coin","image":"https://assets.coingecko.com/coins/images/27045/large/wbt_token.png?1667923752","current_price":5.45,"market_cap":785948998,"market_cap_rank":49,"fully_diluted_valuation":2181396293,"total_volume":12215341,"high_24h":5.63,"low_24h":5.41,"price_change_24h":-0.17489421716929687,"price_change_percentage_24h":-3.10822,"market_cap_change_24h":-28159369.587108493,"market_cap_change_percentage_24h":-3.45892,"circulating_supply":144118517.10815412,"total_supply":368808535.0,"max_supply":400000000.0,"ath":14.64,"ath_change_percentage":-62.75627,"ath_date":"2022-10-28T12:32:18.119Z","atl":3.06,"atl_change_percentage":78.142,"atl_date":"2023-02-13T19:01:21.899Z","roi":null,"last_updated":"2023-08-18T13:46:46.761Z"},{"id":"kaspa","symbol":"kas","name":"Kaspa","image":"https://assets.coingecko.com/coins/images/25751/large/kaspa-icon-exchanges.png?1653891958","current_price":0.03892933,"market_cap":781351834,"market_cap_rank":50,"fully_diluted_valuation":1109567263,"total_volume":15600726,"high_24h":0.03948889,"low_24h":0.03596901,"price_change_24h":0.00037671,"price_change_percentage_24h":0.97713,"market_cap_change_24h":2172371,"market_cap_change_percentage_24h":0.2788,"circulating_supply":20213234996.1091,"total_supply":20213659379.7119,"max_supply":28704026601.0,"ath":0.051714,"ath_change_percentage":-25.85017,"ath_date":"2023-08-06T12:10:40.416Z","atl":0.00017105,"atl_change_percentage":22317.97925,"atl_date":"2022-05-26T14:42:59.316Z","roi":null,"last_updated":"2023-08-18T13:46:41.981Z"},{"id":"algorand","symbol":"algo","name":"Algorand","image":"https://assets.coingecko.com/coins/images/4380/large/download.png?1547039725","current_price":0.096242,"market_cap":753581888,"market_cap_rank":51,"fully_diluted_valuation":962775984,"total_volume":72441722,"high_24h":0.103202,"low_24h":0.090561,"price_change_24h":-0.006959437799724745,"price_change_percentage_24h":-6.74354,"market_cap_change_24h":-55408032.64435506,"market_cap_change_percentage_24h":-6.84904,"circulating_supply":7827177876.26076,"total_supply":7827177870.84676,"max_supply":10000000000.0,"ath":3.56,"ath_change_percentage":-97.2997,"ath_date":"2019-06-20T14:51:19.480Z","atl":0.090561,"atl_change_percentage":6.18444,"atl_date":"2023-08-17T21:51:08.443Z","roi":{"times":-0.9598991098343876,"currency":"usd","percentage":-95.98991098343876},"last_updated":"2023-08-18T13:46:43.985Z"},{"id":"usdd","symbol":"usdd","name":"USDD","image":"https://assets.coingecko.com/coins/images/25380/large/UUSD.jpg?1651823371","current_price":0.995376,"market_cap":721893864,"market_cap_rank":52,"fully_diluted_valuation":null,"total_volume":40320941,"high_24h":1.006,"low_24h":0.988785,"price_change_24h":-0.000361936578527455,"price_change_percentage_24h":-0.03635,"market_cap_change_24h":-1056665.1724659204,"market_cap_change_percentage_24h":-0.14616,"circulating_supply":725332425.525729,"total_supply":null,"max_supply":null,"ath":1.044,"ath_change_percentage":-4.62771,"ath_date":"2022-11-09T09:56:06.131Z","atl":0.928067,"atl_change_percentage":7.277,"atl_date":"2022-06-19T16:15:11.558Z","roi":null,"last_updated":"2023-08-18T13:46:46.508Z"},{"id":"elrond-erd-2","symbol":"egld","name":"MultiversX","image":"https://assets.coingecko.com/coins/images/12335/large/egld-token-logo.png?1673490885","current_price":27.17,"market_cap":701900850,"market_cap_rank":53,"fully_diluted_valuation":853134966,"total_volume":23497326,"high_24h":28.99,"low_24h":25.66,"price_change_24h":-1.8166580468827256,"price_change_percentage_24h":-6.26664,"market_cap_change_24h":-47870216.98417139,"market_cap_change_percentage_24h":-6.38464,"circulating_supply":25846866.0,"total_supply":25852018.0,"max_supply":31415926.0,"ath":545.64,"ath_change_percentage":-95.03307,"ath_date":"2021-11-23T10:33:26.737Z","atl":6.51,"atl_change_percentage":316.5198,"atl_date":"2020-10-07T01:44:53.554Z","roi":null,"last_updated":"2023-08-18T13:46:42.082Z"},{"id":"havven","symbol":"snx","name":"Synthetix Network","image":"https://assets.coingecko.com/coins/images/3406/large/SNX.png?1598631139","current_price":2.16,"market_cap":695138156,"market_cap_rank":54,"fully_diluted_valuation":696700299,"total_volume":47236181,"high_24h":2.26,"low_24h":2.02,"price_change_24h":-0.10041050152564557,"price_change_percentage_24h":-4.43721,"market_cap_change_24h":-34232089.810194016,"market_cap_change_percentage_24h":-4.69338,"circulating_supply":322131898.13952357,"total_supply":322855806.088774,"max_supply":322855806.088774,"ath":28.53,"ath_change_percentage":-92.42869,"ath_date":"2021-02-14T01:12:38.505Z","atl":0.0347864,"atl_change_percentage":6110.0906,"atl_date":"2019-01-06T00:00:00.000Z","roi":{"times":3.32501824544216,"currency":"usd","percentage":332.501824544216},"last_updated":"2023-08-18T13:46:39.773Z"},{"id":"the-sandbox","symbol":"sand","name":"The Sandbox","image":"https://assets.coingecko.com/coins/images/12129/large/sandbox_logo.jpg?1597397942","current_price":0.329292,"market_cap":677391817,"market_cap_rank":55,"fully_diluted_valuation":987484291,"total_volume":101383521,"high_24h":0.355181,"low_24h":0.317189,"price_change_24h":-0.025888515444266454,"price_change_percentage_24h":-7.28883,"market_cap_change_24h":-55219273.62574792,"market_cap_change_percentage_24h":-7.53732,"circulating_supply":2057931926.2233226,"total_supply":3000000000.0,"max_supply":3000000000.0,"ath":8.4,"ath_change_percentage":-96.09809,"ath_date":"2021-11-25T06:04:40.957Z","atl":0.02897764,"atl_change_percentage":1030.64766,"atl_date":"2020-11-04T15:59:14.441Z","roi":null,"last_updated":"2023-08-18T13:46:42.568Z"},{"id":"blockstack","symbol":"stx","name":"Stacks","image":"https://assets.coingecko.com/coins/images/2069/large/Stacks_logo_full.png?1604112510","current_price":0.480864,"market_cap":672809028,"market_cap_rank":56,"fully_diluted_valuation":874154827,"total_volume":30668266,"high_24h":0.518493,"low_24h":0.44961,"price_change_24h":-0.03540229248512944,"price_change_percentage_24h":-6.85738,"market_cap_change_24h":-51808778.818220496,"market_cap_change_percentage_24h":-7.14981,"circulating_supply":1399256487.47318,"total_supply":1818000000.0,"max_supply":1818000000.0,"ath":3.39,"ath_change_percentage":-85.84253,"ath_date":"2021-12-01T01:32:34.725Z","atl":0.04559639,"atl_change_percentage":952.46644,"atl_date":"2020-03-13T02:29:26.415Z","roi":{"times":3.007197108597446,"currency":"usd","percentage":300.71971085974457},"last_updated":"2023-08-18T13:46:37.114Z"},{"id":"immutable-x","symbol":"imx","name":"ImmutableX","image":"https://assets.coingecko.com/coins/images/17233/large/immutableX-symbol-BLK-RGB.png?1665110648","current_price":0.591789,"market_cap":664928990,"market_cap_rank":57,"fully_diluted_valuation":1183789183,"total_volume":29619707,"high_24h":0.641659,"low_24h":0.558233,"price_change_24h":-0.04709335523059898,"price_change_percentage_24h":-7.37121,"market_cap_change_24h":-52803248.34282577,"market_cap_change_percentage_24h":-7.35696,"circulating_supply":1123390886.9500241,"total_supply":2000000000.0,"max_supply":2000000000.0,"ath":9.52,"ath_change_percentage":-93.79863,"ath_date":"2021-11-26T01:03:01.536Z","atl":0.378055,"atl_change_percentage":56.15904,"atl_date":"2022-12-31T07:36:37.649Z","roi":null,"last_updated":"2023-08-18T13:46:41.117Z"},{"id":"tezos","symbol":"xtz","name":"Tezos","image":"https://assets.coingecko.com/coins/images/976/large/Tezos-logo.png?1547034862","current_price":0.698845,"market_cap":658383753,"market_cap_rank":58,"fully_diluted_valuation":null,"total_volume":27403889,"high_24h":0.732552,"low_24h":0.654058,"price_change_24h":-0.033706840299370544,"price_change_percentage_24h":-4.60129,"market_cap_change_24h":-31033893.274683475,"market_cap_change_percentage_24h":-4.50146,"circulating_supply":941114001.30231,"total_supply":null,"max_supply":null,"ath":9.12,"ath_change_percentage":-92.33618,"ath_date":"2021-10-04T00:41:18.025Z","atl":0.350476,"atl_change_percentage":99.34003,"atl_date":"2018-12-07T00:00:00.000Z","roi":{"times":0.48690429376165933,"currency":"usd","percentage":48.69042937616594},"last_updated":"2023-08-18T13:46:42.760Z"},{"id":"eos","symbol":"eos","name":"EOS","image":"https://assets.coingecko.com/coins/images/738/large/eos-eos-logo.png?1547034481","current_price":0.575572,"market_cap":643140995,"market_cap_rank":59,"fully_diluted_valuation":null,"total_volume":182348064,"high_24h":0.637512,"low_24h":0.543797,"price_change_24h":-0.06193985221166809,"price_change_percentage_24h":-9.71588,"market_cap_change_24h":-71028421.67331612,"market_cap_change_percentage_24h":-9.9456,"circulating_supply":1117051244.2007,"total_supply":null,"max_supply":null,"ath":22.71,"ath_change_percentage":-97.46688,"ath_date":"2018-04-29T07:50:33.540Z","atl":0.5024,"atl_change_percentage":14.51111,"atl_date":"2017-10-23T00:00:00.000Z","roi":{"times":-0.41861442537047444,"currency":"usd","percentage":-41.861442537047445},"last_updated":"2023-08-18T13:46:40.906Z"},{"id":"injective-protocol","symbol":"inj","name":"Injective","image":"https://assets.coingecko.com/coins/images/12882/large/Secondary_Symbol.png?1628233237","current_price":7.66,"market_cap":641773261,"market_cap_rank":60,"fully_diluted_valuation":766245602,"total_volume":94879469,"high_24h":7.71,"low_24h":6.8,"price_change_24h":0.572466,"price_change_percentage_24h":8.07492,"market_cap_change_24h":46344225,"market_cap_change_percentage_24h":7.78333,"circulating_supply":83755555.66,"total_supply":100000000.0,"max_supply":100000000.0,"ath":24.89,"ath_change_percentage":-69.37316,"ath_date":"2021-04-30T00:33:02.969Z","atl":0.657401,"atl_change_percentage":1059.56354,"atl_date":"2020-11-03T16:19:30.576Z","roi":null,"last_updated":"2023-08-18T13:46:44.464Z"},{"id":"axie-infinity","symbol":"axs","name":"Axie Infinity","image":"https://assets.coingecko.com/coins/images/13029/large/axie_infinity_logo.png?1604471082","current_price":4.87,"market_cap":639256073,"market_cap_rank":61,"fully_diluted_valuation":1317231398,"total_volume":54560974,"high_24h":5.32,"low_24h":4.71,"price_change_24h":-0.43996942782104664,"price_change_percentage_24h":-8.2828,"market_cap_change_24h":-59773007.13749015,"market_cap_change_percentage_24h":-8.55086,"circulating_supply":131031753.30627233,"total_supply":270000000.0,"max_supply":270000000.0,"ath":164.9,"ath_change_percentage":-97.06195,"ath_date":"2021-11-06T19:29:29.482Z","atl":0.123718,"atl_change_percentage":3815.97435,"atl_date":"2020-11-06T08:05:43.662Z","roi":null,"last_updated":"2023-08-18T13:46:45.301Z"},{"id":"theta-token","symbol":"theta","name":"Theta Network","image":"https://assets.coingecko.com/coins/images/2538/large/theta-token-logo.png?1548387191","current_price":0.635752,"market_cap":635705316,"market_cap_rank":62,"fully_diluted_valuation":635705316,"total_volume":22666459,"high_24h":0.675338,"low_24h":0.599697,"price_change_24h":-0.03958612114462767,"price_change_percentage_24h":-5.86167,"market_cap_change_24h":-41306602.388717294,"market_cap_change_percentage_24h":-6.10131,"circulating_supply":1000000000.0,"total_supply":1000000000.0,"max_supply":1000000000.0,"ath":15.72,"ath_change_percentage":-95.95625,"ath_date":"2021-04-16T13:15:11.190Z","atl":0.04039979,"atl_change_percentage":1473.43797,"atl_date":"2020-03-13T02:24:16.483Z","roi":{"times":3.2383476452022206,"currency":"usd","percentage":323.83476452022205},"last_updated":"2023-08-18T13:46:39.057Z"},{"id":"flex-coin","symbol":"flex","name":"FLEX Coin","image":"https://assets.coingecko.com/coins/images/9108/large/coinflex_logo.png?1628750583","current_price":6.31,"market_cap":620558982,"market_cap_rank":63,"fully_diluted_valuation":621004448,"total_volume":165836,"high_24h":7.14,"low_24h":5.6,"price_change_24h":0.218171,"price_change_percentage_24h":3.58207,"market_cap_change_24h":12881862,"market_cap_change_percentage_24h":2.11985,"circulating_supply":98664938.6988896,"total_supply":98735764.894,"max_supply":98735764.894,"ath":12.32,"ath_change_percentage":-49.15315,"ath_date":"2023-08-07T01:49:53.752Z","atl":0.00047299,"atl_change_percentage":1324456.2487,"atl_date":"2020-08-04T11:18:39.614Z","roi":null,"last_updated":"2023-08-18T13:46:26.278Z"},{"id":"bitget-token","symbol":"bgb","name":"Bitget Token","image":"https://assets.coingecko.com/coins/images/11610/large/icon_colour.png?1690515455","current_price":0.424502,"market_cap":594269622,"market_cap_rank":64,"fully_diluted_valuation":848955996,"total_volume":15146694,"high_24h":0.442007,"low_24h":0.411852,"price_change_24h":-0.017504831509135843,"price_change_percentage_24h":-3.9603,"market_cap_change_24h":-27492411.969072223,"market_cap_change_percentage_24h":-4.42169,"circulating_supply":1400001000.0,"total_supply":2000000000.0,"max_supply":2000000000.0,"ath":0.515471,"ath_change_percentage":-17.48537,"ath_date":"2023-02-16T08:52:49.445Z","atl":0.0142795,"atl_change_percentage":2878.66942,"atl_date":"2020-06-25T04:17:05.895Z","roi":null,"last_updated":"2023-08-18T13:46:14.417Z"},{"id":"apecoin","symbol":"ape","name":"ApeCoin","image":"https://assets.coingecko.com/coins/images/24383/large/apecoin.jpg?1647476455","current_price":1.59,"market_cap":585511967,"market_cap_rank":65,"fully_diluted_valuation":1588502157,"total_volume":164783498,"high_24h":1.83,"low_24h":1.47,"price_change_24h":-0.19160002239680418,"price_change_percentage_24h":-10.75532,"market_cap_change_24h":-73309074.13630581,"market_cap_change_percentage_24h":-11.12731,"circulating_supply":368593750.0,"total_supply":1000000000.0,"max_supply":1000000000.0,"ath":26.7,"ath_change_percentage":-94.04416,"ath_date":"2022-04-28T21:44:21.164Z","atl":1.47,"atl_change_percentage":8.02338,"atl_date":"2023-08-17T21:45:24.136Z","roi":null,"last_updated":"2023-08-18T13:46:42.304Z"},{"id":"decentraland","symbol":"mana","name":"Decentraland","image":"https://assets.coingecko.com/coins/images/878/large/decentraland-mana.png?1550108745","current_price":0.306598,"market_cap":564943270,"market_cap_rank":66,"fully_diluted_valuation":672621501,"total_volume":84587495,"high_24h":0.329998,"low_24h":0.291523,"price_change_24h":-0.02340030731522441,"price_change_percentage_24h":-7.09104,"market_cap_change_24h":-45079611.84259415,"market_cap_change_percentage_24h":-7.38982,"circulating_supply":1842078939.5143201,"total_supply":2193179327.32015,"max_supply":2193179327.32015,"ath":5.85,"ath_change_percentage":-94.76315,"ath_date":"2021-11-25T10:04:18.534Z","atl":0.00923681,"atl_change_percentage":3217.14715,"atl_date":"2017-10-31T00:00:00.000Z","roi":{"times":14.329905166758614,"currency":"usd","percentage":1432.9905166758615},"last_updated":"2023-08-18T13:46:42.192Z"},{"id":"bitcoin-cash-sv","symbol":"bsv","name":"Bitcoin SV","image":"https://assets.coingecko.com/coins/images/6799/large/BSV.png?1558947902","current_price":28.93,"market_cap":557979254,"market_cap_rank":67,"fully_diluted_valuation":608196705,"total_volume":43589539,"high_24h":31.33,"low_24h":26.36,"price_change_24h":-2.4028587912480077,"price_change_percentage_24h":-7.66946,"market_cap_change_24h":-46695345.34583068,"market_cap_change_percentage_24h":-7.72239,"circulating_supply":19266076.644239,"total_supply":21000000.0,"max_supply":21000000.0,"ath":489.75,"ath_change_percentage":-94.10967,"ath_date":"2021-04-16T17:09:04.630Z","atl":21.43,"atl_change_percentage":34.58431,"atl_date":"2023-06-10T04:32:12.266Z","roi":null,"last_updated":"2023-08-18T13:46:41.544Z"},{"id":"fantom","symbol":"ftm","name":"Fantom","image":"https://assets.coingecko.com/coins/images/4001/large/Fantom_round.png?1669652346","current_price":0.197945,"market_cap":554486706,"market_cap_rank":68,"fully_diluted_valuation":628253483,"total_volume":124864875,"high_24h":0.216746,"low_24h":0.186814,"price_change_24h":-0.01880059041871568,"price_change_percentage_24h":-8.67403,"market_cap_change_24h":-54463608.50391066,"market_cap_change_percentage_24h":-8.94385,"circulating_supply":2802205385.26394,"total_supply":3175000000.0,"max_supply":3175000000.0,"ath":3.46,"ath_change_percentage":-94.28479,"ath_date":"2021-10-28T05:19:39.845Z","atl":0.00190227,"atl_change_percentage":10291.0023,"atl_date":"2020-03-13T02:25:38.280Z","roi":{"times":5.598173137481713,"currency":"usd","percentage":559.8173137481714},"last_updated":"2023-08-18T13:46:39.450Z"},{"id":"radix","symbol":"xrd","name":"Radix","image":"https://assets.coingecko.com/coins/images/4374/large/Radix.png?1629701658","current_price":0.051974,"market_cap":532758863,"market_cap_rank":69,"fully_diluted_valuation":1249150649,"total_volume":2246974,"high_24h":0.054553,"low_24h":0.05178,"price_change_24h":-0.002562611557608535,"price_change_percentage_24h":-4.69885,"market_cap_change_24h":-26920697.95472783,"market_cap_change_percentage_24h":-4.81002,"circulating_supply":10235925273.047,"total_supply":12635925268.7514,"max_supply":24000000000.0,"ath":0.651264,"ath_change_percentage":-92.02444,"ath_date":"2021-11-14T16:09:27.130Z","atl":0.03145312,"atl_change_percentage":65.14082,"atl_date":"2022-11-29T23:20:09.754Z","roi":null,"last_updated":"2023-08-18T13:46:44.657Z"},{"id":"render-token","symbol":"rndr","name":"Render","image":"https://assets.coingecko.com/coins/images/11636/large/rndr.png?1638840934","current_price":1.43,"market_cap":531247562,"market_cap_rank":70,"fully_diluted_valuation":758534384,"total_volume":43735880,"high_24h":1.58,"low_24h":1.34,"price_change_24h":-0.1517171794469907,"price_change_percentage_24h":-9.6143,"market_cap_change_24h":-56879103.51336014,"market_cap_change_percentage_24h":-9.67123,"circulating_supply":371908453.108796,"total_supply":531024271.388796,"max_supply":531024271.388796,"ath":8.78,"ath_change_percentage":-83.78401,"ath_date":"2021-11-21T10:03:19.097Z","atl":0.03665669,"atl_change_percentage":3785.38063,"atl_date":"2020-06-16T13:22:25.900Z","roi":null,"last_updated":"2023-08-18T13:46:38.379Z"},{"id":"gatechain-token","symbol":"gt","name":"Gate","image":"https://assets.coingecko.com/coins/images/8183/large/gate.png?1687143308","current_price":3.85,"market_cap":526910261,"market_cap_rank":71,"fully_diluted_valuation":1150730659,"total_volume":1120057,"high_24h":4.0,"low_24h":3.84,"price_change_24h":-0.15735157871395034,"price_change_percentage_24h":-3.93092,"market_cap_change_24h":-23159095.124231398,"market_cap_change_percentage_24h":-4.21021,"circulating_supply":137367573.56752193,"total_supply":300000000.0,"max_supply":null,"ath":12.94,"ath_change_percentage":-70.27858,"ath_date":"2021-05-12T11:39:16.531Z","atl":0.25754,"atl_change_percentage":1393.55463,"atl_date":"2020-03-13T02:18:02.481Z","roi":null,"last_updated":"2023-08-18T13:46:43.240Z"},{"id":"paxos-standard","symbol":"usdp","name":"Pax Dollar","image":"https://assets.coingecko.com/coins/images/6013/large/Pax_Dollar.png?1629877204","current_price":0.999678,"market_cap":505954031,"market_cap_rank":72,"fully_diluted_valuation":505954031,"total_volume":2520952,"high_24h":1.01,"low_24h":0.986685,"price_change_24h":-0.000585974597436367,"price_change_percentage_24h":-0.05858,"market_cap_change_24h":-761700.2296261787,"market_cap_change_percentage_24h":-0.15032,"circulating_supply":506100005.200683,"total_supply":506100005.200683,"max_supply":null,"ath":1.13,"ath_change_percentage":-11.35008,"ath_date":"2018-10-15T07:09:12.459Z","atl":0.863529,"atl_change_percentage":15.76713,"atl_date":"2021-05-19T13:14:42.046Z","roi":{"times":-0.0003221341145643,"currency":"usd","percentage":-0.03221341145643},"last_updated":"2023-08-18T13:46:37.148Z"},{"id":"rocket-pool","symbol":"rpl","name":"Rocket Pool","image":"https://assets.coingecko.com/coins/images/2090/large/rocket_pool_%28RPL%29.png?1637662441","current_price":25.4,"market_cap":498790675,"market_cap_rank":73,"fully_diluted_valuation":498790675,"total_volume":5485488,"high_24h":27.05,"low_24h":24.25,"price_change_24h":-1.643785799564636,"price_change_percentage_24h":-6.07723,"market_cap_change_24h":-32304924.115449667,"market_cap_change_percentage_24h":-6.08269,"circulating_supply":19620795.3927166,"total_supply":19620795.3927166,"max_supply":null,"ath":61.9,"ath_change_percentage":-58.96667,"ath_date":"2023-04-16T19:20:19.534Z","atl":0.00884718,"atl_change_percentage":286983.38524,"atl_date":"2018-08-28T00:00:00.000Z","roi":null,"last_updated":"2023-08-18T13:46:38.401Z"},{"id":"gala","symbol":"gala","name":"GALA","image":"https://assets.coingecko.com/coins/images/12493/large/GALA-COINGECKO.png?1600233435","current_price":0.01952811,"market_cap":496233293,"market_cap_rank":74,"fully_diluted_valuation":976490006,"total_volume":815575404,"high_24h":0.02078095,"low_24h":0.01770042,"price_change_24h":-0.001095748254375788,"price_change_percentage_24h":-5.31301,"market_cap_change_24h":-28835279.969957948,"market_cap_change_percentage_24h":-5.49172,"circulating_supply":25409030794.0509,"total_supply":25409575452.9257,"max_supply":50000000000.0,"ath":0.824837,"ath_change_percentage":-97.64288,"ath_date":"2021-11-26T01:03:48.731Z","atl":0.00013475,"atl_change_percentage":14328.56057,"atl_date":"2020-12-28T08:46:48.367Z","roi":null,"last_updated":"2023-08-18T13:46:45.387Z"},{"id":"rollbit-coin","symbol":"rlb","name":"Rollbit Coin","image":"https://assets.coingecko.com/coins/images/24552/large/unziL6wO_400x400.jpg?1648134494","current_price":0.150854,"market_cap":495913803,"market_cap_rank":75,"fully_diluted_valuation":752079285,"total_volume":20688521,"high_24h":0.168772,"low_24h":0.139567,"price_change_24h":-0.007743673340513847,"price_change_percentage_24h":-4.8826,"market_cap_change_24h":-27260792.063461483,"market_cap_change_percentage_24h":-5.21065,"circulating_supply":3296951621.59,"total_supply":3296951622.0,"max_supply":5000000000.0,"ath":0.213089,"ath_change_percentage":-29.28749,"ath_date":"2023-08-12T14:31:00.633Z","atl":0.00093506,"atl_change_percentage":16014.57689,"atl_date":"2022-07-02T02:46:34.730Z","roi":null,"last_updated":"2023-08-18T13:46:35.565Z"},{"id":"neo","symbol":"neo","name":"NEO","image":"https://assets.coingecko.com/coins/images/480/large/NEO_512_512.png?1594357361","current_price":6.96,"market_cap":490905541,"market_cap_rank":76,"fully_diluted_valuation":696023736,"total_volume":44065717,"high_24h":7.66,"low_24h":6.78,"price_change_24h":-0.699006258954654,"price_change_percentage_24h":-9.12622,"market_cap_change_24h":-50989120.58609009,"market_cap_change_percentage_24h":-9.40942,"circulating_supply":70530000.0,"total_supply":100000000.0,"max_supply":null,"ath":198.38,"ath_change_percentage":-96.49247,"ath_date":"2018-01-15T00:00:00.000Z","atl":0.078349,"atl_change_percentage":8781.09348,"atl_date":"2016-10-21T00:00:00.000Z","roi":{"times":192.3419851973812,"currency":"usd","percentage":19234.19851973812},"last_updated":"2023-08-18T13:46:42.129Z"},{"id":"kava","symbol":"kava","name":"Kava","image":"https://assets.coingecko.com/coins/images/9761/large/kava.png?1663638871","current_price":0.692424,"market_cap":485920244,"market_cap_rank":77,"fully_diluted_valuation":485902951,"total_volume":33397981,"high_24h":0.764623,"low_24h":0.63485,"price_change_24h":-0.06860344785986372,"price_change_percentage_24h":-9.01458,"market_cap_change_24h":-53874860.42446357,"market_cap_change_percentage_24h":-9.98061,"circulating_supply":702519936.0,"total_supply":702582596.0,"max_supply":null,"ath":9.12,"ath_change_percentage":-92.45344,"ath_date":"2021-08-30T11:10:02.948Z","atl":0.287137,"atl_change_percentage":139.69914,"atl_date":"2020-03-13T02:24:16.835Z","roi":null,"last_updated":"2023-08-18T13:46:40.791Z"},{"id":"compound-ether","symbol":"ceth","name":"cETH","image":"https://assets.coingecko.com/coins/images/10643/large/ceth.png?1687143191","current_price":33.69,"market_cap":473162072,"market_cap_rank":78,"fully_diluted_valuation":473162072,"total_volume":8357.81,"high_24h":35.83,"low_24h":32.44,"price_change_24h":-2.1379741156292553,"price_change_percentage_24h":-5.96728,"market_cap_change_24h":-10482692.842676222,"market_cap_change_percentage_24h":-2.16744,"circulating_supply":14044465.8362955,"total_supply":14044465.8362955,"max_supply":null,"ath":97.75,"ath_change_percentage":-65.53443,"ath_date":"2021-11-21T12:39:57.508Z","atl":1.89,"atl_change_percentage":1686.06253,"atl_date":"2020-03-13T02:22:33.711Z","roi":null,"last_updated":"2023-08-18T13:46:20.331Z"},{"id":"pax-gold","symbol":"paxg","name":"PAX Gold","image":"https://assets.coingecko.com/coins/images/9519/large/paxgold.png?1687143101","current_price":1887.99,"market_cap":469517312,"market_cap_rank":79,"fully_diluted_valuation":469517312,"total_volume":18090591,"high_24h":1898.91,"low_24h":1837.95,"price_change_24h":-6.922215889132758,"price_change_percentage_24h":-0.36531,"market_cap_change_24h":-2483609.858515501,"market_cap_change_percentage_24h":-0.52619,"circulating_supply":248753.694,"total_supply":248753.694,"max_supply":null,"ath":2241.37,"ath_change_percentage":-15.76432,"ath_date":"2021-05-17T19:02:29.657Z","atl":1399.64,"atl_change_percentage":34.89402,"atl_date":"2019-11-18T03:09:35.959Z","roi":null,"last_updated":"2023-08-18T13:46:43.755Z"},{"id":"kucoin-shares","symbol":"kcs","name":"KuCoin","image":"https://assets.coingecko.com/coins/images/1047/large/sa9z79.png?1610678720","current_price":4.84,"market_cap":467785085,"market_cap_rank":80,"fully_diluted_valuation":697487406,"total_volume":2835141,"high_24h":5.17,"low_24h":4.75,"price_change_24h":-0.2790380852660874,"price_change_percentage_24h":-5.45529,"market_cap_change_24h":-27979770.9267323,"market_cap_change_percentage_24h":-5.64376,"circulating_supply":96732986.425851,"total_supply":144232986.425767,"max_supply":null,"ath":28.83,"ath_change_percentage":-83.22205,"ath_date":"2021-12-01T15:09:35.541Z","atl":0.342863,"atl_change_percentage":1310.78629,"atl_date":"2019-02-07T00:00:00.000Z","roi":null,"last_updated":"2023-08-18T13:46:20.973Z"},{"id":"tether-gold","symbol":"xaut","name":"Tether Gold","image":"https://assets.coingecko.com/coins/images/10481/large/Tether_Gold.png?1668148656","current_price":1893.96,"market_cap":466848162,"market_cap_rank":81,"fully_diluted_valuation":466848162,"total_volume":13611172,"high_24h":1901.07,"low_24h":1870.61,"price_change_24h":-4.513049046841843,"price_change_percentage_24h":-0.23772,"market_cap_change_24h":-2277760.593694091,"market_cap_change_percentage_24h":-0.48553,"circulating_supply":246524.33,"total_supply":246524.33,"max_supply":null,"ath":2169.74,"ath_change_percentage":-12.70928,"ath_date":"2023-03-15T20:36:21.941Z","atl":1447.84,"atl_change_percentage":30.81421,"atl_date":"2020-03-19T13:45:41.821Z","roi":null,"last_updated":"2023-08-18T13:46:46.502Z"},{"id":"flow","symbol":"flow","name":"Flow","image":"https://assets.coingecko.com/coins/images/13446/large/5f6294c0c7a8cda55cb1c936_Flow_Wordmark.png?1631696776","current_price":0.44957,"market_cap":466084572,"market_cap_rank":82,"fully_diluted_valuation":652508053,"total_volume":22629150,"high_24h":0.489615,"low_24h":0.431078,"price_change_24h":-0.039569559679448245,"price_change_percentage_24h":-8.08963,"market_cap_change_24h":-41559440.818280876,"market_cap_change_percentage_24h":-8.18673,"circulating_supply":1036200000.0,"total_supply":1450656993.87114,"max_supply":1450656993.87114,"ath":42.4,"ath_change_percentage":-98.94188,"ath_date":"2021-04-05T13:49:10.098Z","atl":0.431078,"atl_change_percentage":4.06759,"atl_date":"2023-08-17T22:15:05.867Z","roi":null,"last_updated":"2023-08-18T13:46:36.403Z"},{"id":"ecash","symbol":"xec","name":"eCash","image":"https://assets.coingecko.com/coins/images/16646/large/Logo_final-22.png?1628239446","current_price":2.355e-05,"market_cap":463310959,"market_cap_rank":83,"fully_diluted_valuation":499626241,"total_volume":7337848,"high_24h":2.591e-05,"low_24h":2.253e-05,"price_change_24h":-2.365724895318e-06,"price_change_percentage_24h":-9.12964,"market_cap_change_24h":-39412060.51602125,"market_cap_change_percentage_24h":-7.83972,"circulating_supply":19473617173093.0,"total_supply":21000000000000.0,"max_supply":21000000000000.0,"ath":0.00038001,"ath_change_percentage":-93.82728,"ath_date":"2021-09-04T17:09:31.137Z","atl":1.847e-05,"atl_change_percentage":27.00194,"atl_date":"2021-07-20T20:49:46.212Z","roi":null,"last_updated":"2023-08-18T13:46:05.148Z"},{"id":"pepe","symbol":"pepe","name":"Pepe","image":"https://assets.coingecko.com/coins/images/29850/large/pepe-token.jpeg?1682922725","current_price":1.1e-06,"market_cap":461462047,"market_cap_rank":84,"fully_diluted_valuation":461462047,"total_volume":168268853,"high_24h":1.2e-06,"low_24h":1.01e-06,"price_change_24h":-1.01077490603e-07,"price_change_percentage_24h":-8.43614,"market_cap_change_24h":-43997811.341879964,"market_cap_change_percentage_24h":-8.70451,"circulating_supply":420690000000000.0,"total_supply":420690000000000.0,"max_supply":420690000000000.0,"ath":4.31e-06,"ath_change_percentage":-74.56433,"ath_date":"2023-05-05T16:50:45.302Z","atl":5.5142e-08,"atl_change_percentage":1886.74251,"atl_date":"2023-04-18T02:14:41.591Z","roi":null,"last_updated":"2023-08-18T13:46:38.194Z"},{"id":"klay-token","symbol":"klay","name":"Klaytn","image":"https://assets.coingecko.com/coins/images/9672/large/klaytn.png?1660288824","current_price":0.140653,"market_cap":449184403,"market_cap_rank":85,"fully_diluted_valuation":null,"total_volume":16315686,"high_24h":0.147547,"low_24h":0.132074,"price_change_24h":-0.006894217964395545,"price_change_percentage_24h":-4.67256,"market_cap_change_24h":-23493366.83234185,"market_cap_change_percentage_24h":-4.97027,"circulating_supply":3194512384.0609,"total_supply":null,"max_supply":null,"ath":4.34,"ath_change_percentage":-96.76527,"ath_date":"2021-03-30T03:44:28.828Z","atl":0.06044,"atl_change_percentage":132.21904,"atl_date":"2020-04-29T08:19:34.574Z","roi":null,"last_updated":"2023-08-18T13:46:43.696Z"},{"id":"chiliz","symbol":"chz","name":"Chiliz","image":"https://assets.coingecko.com/coins/images/8834/large/CHZ_Token_updated.png?1675848257","current_price":0.063775,"market_cap":445395407,"market_cap_rank":86,"fully_diluted_valuation":567555983,"total_volume":67650072,"high_24h":0.068659,"low_24h":0.060225,"price_change_24h":-0.004847197278445889,"price_change_percentage_24h":-7.06358,"market_cap_change_24h":-35152965.34636921,"market_cap_change_percentage_24h":-7.31518,"circulating_supply":6975647158.46,"total_supply":8888888888.0,"max_supply":8888888888.0,"ath":0.878633,"ath_change_percentage":-92.77457,"ath_date":"2021-03-13T08:04:21.200Z","atl":0.00410887,"atl_change_percentage":1445.07153,"atl_date":"2019-09-28T00:00:00.000Z","roi":{"times":1.898871383808577,"currency":"usd","percentage":189.8871383808577},"last_updated":"2023-08-18T13:46:37.487Z"},{"id":"thorchain","symbol":"rune","name":"THORChain","image":"https://assets.coingecko.com/coins/images/6595/large/Rune200x200.png?1671179394","current_price":1.47,"market_cap":443343718,"market_cap_rank":87,"fully_diluted_valuation":737184721,"total_volume":143948136,"high_24h":1.61,"low_24h":1.44,"price_change_24h":-0.062111255826571954,"price_change_percentage_24h":-4.04363,"market_cap_change_24h":-21609082.523587048,"market_cap_change_percentage_24h":-4.64759,"circulating_supply":300700561.0,"total_supply":500000000.0,"max_supply":500000000.0,"ath":20.87,"ath_change_percentage":-92.93681,"ath_date":"2021-05-19T00:30:09.436Z","atl":0.00851264,"atl_change_percentage":17214.45307,"atl_date":"2019-09-28T00:00:00.000Z","roi":{"times":37.78728454792782,"currency":"usd","percentage":3778.7284547927816},"last_updated":"2023-08-18T13:46:41.799Z"},{"id":"frax-share","symbol":"fxs","name":"Frax Share","image":"https://assets.coingecko.com/coins/images/13423/large/Frax_Shares_icon.png?1679886947","current_price":5.87,"market_cap":427764789,"market_cap_rank":88,"fully_diluted_valuation":585415073,"total_volume":39949455,"high_24h":6.3,"low_24h":5.52,"price_change_24h":-0.4074059951704232,"price_change_percentage_24h":-6.49055,"market_cap_change_24h":-30911065.155724287,"market_cap_change_percentage_24h":-6.7392,"circulating_supply":72837645.1145934,"total_supply":99681545.5911336,"max_supply":99681545.5911336,"ath":42.8,"ath_change_percentage":-86.34069,"ath_date":"2022-01-12T15:22:27.465Z","atl":1.5,"atl_change_percentage":288.92415,"atl_date":"2021-06-25T16:50:51.447Z","roi":null,"last_updated":"2023-08-18T13:46:38.565Z"},{"id":"curve-dao-token","symbol":"crv","name":"Curve DAO","image":"https://assets.coingecko.com/coins/images/12124/large/Curve.png?1597369484","current_price":0.499704,"market_cap":426477492,"market_cap_rank":89,"fully_diluted_valuation":1650545754,"total_volume":110914800,"high_24h":0.53957,"low_24h":0.477582,"price_change_24h":-0.03986666504807845,"price_change_percentage_24h":-7.38859,"market_cap_change_24h":-34840889.40093827,"market_cap_change_percentage_24h":-7.55246,"circulating_supply":853455940.0,"total_supply":1997919530.17712,"max_supply":3303030299.0,"ath":15.37,"ath_change_percentage":-96.75981,"ath_date":"2020-08-14T00:00:00.000Z","atl":0.331577,"atl_change_percentage":50.21718,"atl_date":"2020-11-05T13:09:50.181Z","roi":null,"last_updated":"2023-08-18T13:46:37.155Z"},{"id":"frax-ether","symbol":"frxeth","name":"Frax Ether","image":"https://assets.coingecko.com/coins/images/28284/large/frxETH_icon.png?1679886981","current_price":1676.16,"market_cap":422217321,"market_cap_rank":90,"fully_diluted_valuation":422227895,"total_volume":8291647,"high_24h":1783.13,"low_24h":1591.4,"price_change_24h":-106.36758623727337,"price_change_percentage_24h":-5.96724,"market_cap_change_24h":-26549085.88081187,"market_cap_change_percentage_24h":-5.91601,"circulating_supply":251767.635955801,"total_supply":251773.941500941,"max_supply":null,"ath":2134.61,"ath_change_percentage":-21.5964,"ath_date":"2023-04-16T19:24:52.171Z","atl":1137.25,"atl_change_percentage":47.1634,"atl_date":"2022-11-23T02:25:33.267Z","roi":null,"last_updated":"2023-08-18T13:46:24.618Z"},{"id":"bittorrent","symbol":"btt","name":"BitTorrent","image":"https://assets.coingecko.com/coins/images/22457/large/btt_logo.png?1643857231","current_price":4.26721e-07,"market_cap":408070234,"market_cap_rank":91,"fully_diluted_valuation":424616682,"total_volume":23800387,"high_24h":4.44613e-07,"low_24h":4.2498e-07,"price_change_24h":-1.7492815201e-08,"price_change_percentage_24h":-3.93792,"market_cap_change_24h":-14551838.415798664,"market_cap_change_percentage_24h":-3.44323,"circulating_supply":951421714286000.0,"total_supply":990000000000000.0,"max_supply":990000000000000.0,"ath":3.43e-06,"ath_change_percentage":-87.51935,"ath_date":"2022-01-21T04:00:31.909Z","atl":4.2498e-07,"atl_change_percentage":0.77038,"atl_date":"2023-08-17T23:50:26.801Z","roi":null,"last_updated":"2023-08-18T13:46:39.170Z"},{"id":"casper-network","symbol":"cspr","name":"Casper Network","image":"https://assets.coingecko.com/coins/images/15279/large/casper.PNG?1620341020","current_price":0.03577592,"market_cap":403109008,"market_cap_rank":92,"fully_diluted_valuation":427789905,"total_volume":6983963,"high_24h":0.03704507,"low_24h":0.03511044,"price_change_24h":-0.000995752617504238,"price_change_percentage_24h":-2.70793,"market_cap_change_24h":-10965994.125239313,"market_cap_change_percentage_24h":-2.64831,"circulating_supply":11255231041.0,"total_supply":11944550794.0,"max_supply":null,"ath":1.33,"ath_change_percentage":-97.29667,"ath_date":"2021-05-12T00:00:00.000Z","atl":0.02241297,"atl_change_percentage":59.86825,"atl_date":"2022-06-18T20:14:44.694Z","roi":null,"last_updated":"2023-08-18T13:45:13.738Z"},{"id":"tokenize-xchange","symbol":"tkx","name":"Tokenize Xchange","image":"https://assets.coingecko.com/coins/images/4984/large/TKX_-_Logo_-_RGB-15.png?1672912391","current_price":5.01,"market_cap":401893087,"market_cap_rank":93,"fully_diluted_valuation":502391479,"total_volume":9000981,"high_24h":5.4,"low_24h":4.76,"price_change_24h":-0.3754176103999205,"price_change_percentage_24h":-6.9647,"market_cap_change_24h":-29312245.887512326,"market_cap_change_percentage_24h":-6.79775,"circulating_supply":79995999.94518414,"total_supply":100000000.0,"max_supply":100000000.0,"ath":22.3,"ath_change_percentage":-77.5226,"ath_date":"2022-10-31T10:23:59.455Z","atl":0.111255,"atl_change_percentage":4404.63061,"atl_date":"2019-04-28T00:00:00.000Z","roi":{"times":16.262902403876094,"currency":"usd","percentage":1626.2902403876094},"last_updated":"2023-08-18T13:46:32.620Z"},{"id":"iota","symbol":"miota","name":"IOTA","image":"https://assets.coingecko.com/coins/images/692/large/IOTA_Swirl.png?1604238557","current_price":0.143038,"market_cap":397502855,"market_cap_rank":94,"fully_diluted_valuation":397502855,"total_volume":10627674,"high_24h":0.155251,"low_24h":0.137309,"price_change_24h":-0.012213357447133172,"price_change_percentage_24h":-7.86683,"market_cap_change_24h":-34646895.04480052,"market_cap_change_percentage_24h":-8.01734,"circulating_supply":2779530283.277761,"total_supply":2779530283.0,"max_supply":null,"ath":5.25,"ath_change_percentage":-97.27644,"ath_date":"2017-12-19T00:00:00.000Z","atl":0.081637,"atl_change_percentage":75.10812,"atl_date":"2020-03-13T02:22:41.168Z","roi":{"times":3.0617901643416463,"currency":"btc","percentage":306.1790164341646},"last_updated":"2023-08-18T13:46:40.795Z"},{"id":"mina-protocol","symbol":"mina","name":"Mina Protocol","image":"https://assets.coingecko.com/coins/images/15628/large/JM4_vQ34_400x400.png?1621394004","current_price":0.406258,"market_cap":386887061,"market_cap_rank":95,"fully_diluted_valuation":432246373,"total_volume":16471584,"high_24h":0.430925,"low_24h":0.372282,"price_change_24h":-0.024404344612820646,"price_change_percentage_24h":-5.6667,"market_cap_change_24h":-24744341.657311797,"market_cap_change_percentage_24h":-6.01129,"circulating_supply":952909558.840039,"total_supply":1064630332.84004,"max_supply":null,"ath":9.09,"ath_change_percentage":-95.54999,"ath_date":"2021-06-01T01:42:37.064Z","atl":0.372282,"atl_change_percentage":8.66013,"atl_date":"2023-08-17T21:49:55.138Z","roi":null,"last_updated":"2023-08-18T13:46:36.908Z"},{"id":"huobi-token","symbol":"ht","name":"Huobi","image":"https://assets.coingecko.com/coins/images/2822/large/huobi-token-logo.png?1547036992","current_price":2.34,"market_cap":373304599,"market_cap_rank":96,"fully_diluted_valuation":470828284,"total_volume":6567584,"high_24h":2.5,"low_24h":2.31,"price_change_24h":-0.1487038675613328,"price_change_percentage_24h":-5.96626,"market_cap_change_24h":-24806056.562996745,"market_cap_change_percentage_24h":-6.23095,"circulating_supply":159406077.0,"total_supply":201050000.0,"max_supply":201050000.0,"ath":39.66,"ath_change_percentage":-94.09164,"ath_date":"2021-05-12T14:42:21.586Z","atl":0.3138,"atl_change_percentage":646.75019,"atl_date":"2023-03-10T05:05:00+08:00","roi":{"times":1.3673820792216889,"currency":"usd","percentage":136.7382079221689},"last_updated":"2023-08-18T13:46:44.767Z"},{"id":"terra-luna","symbol":"lunc","name":"Terra Luna Classic","image":"https://assets.coingecko.com/coins/images/8284/large/01_LunaClassic_color.png?1653547790","current_price":6.282e-05,"market_cap":365260938,"market_cap_rank":97,"fully_diluted_valuation":429492429,"total_volume":44391161,"high_24h":6.689e-05,"low_24h":5.76e-05,"price_change_24h":-3.874059124677e-06,"price_change_percentage_24h":-5.80902,"market_cap_change_24h":-23123165.17619604,"market_cap_change_percentage_24h":-5.95368,"circulating_supply":5815677633014.15,"total_supply":6838370211447.06,"max_supply":null,"ath":119.18,"ath_change_percentage":-99.99995,"ath_date":"2022-04-05T12:24:58.854Z","atl":9.99967e-07,"atl_change_percentage":6137.19797,"atl_date":"2022-05-13T02:34:40.340Z","roi":null,"last_updated":"2023-08-18T13:46:44.608Z"},{"id":"gemini-dollar","symbol":"gusd","name":"Gemini Dollar","image":"https://assets.coingecko.com/coins/images/5992/large/gemini-dollar-gusd.png?1536745278","current_price":0.997709,"market_cap":360786737,"market_cap_rank":98,"fully_diluted_valuation":360786737,"total_volume":301464,"high_24h":1.011,"low_24h":0.969898,"price_change_24h":-0.000431263639132484,"price_change_percentage_24h":-0.04321,"market_cap_change_24h":-1064270.0585516095,"market_cap_change_percentage_24h":-0.29412,"circulating_supply":361442518.3,"total_supply":361442518.3,"max_supply":null,"ath":3.3,"ath_change_percentage":-69.80176,"ath_date":"2018-10-11T17:36:21.529Z","atl":0.78261,"atl_change_percentage":27.4848,"atl_date":"2018-09-29T00:00:00.000Z","roi":{"times":-0.0022914918170576,"currency":"usd","percentage":-0.22914918170576},"last_updated":"2023-08-18T13:46:43.476Z"},{"id":"trust-wallet-token","symbol":"twt","name":"Trust Wallet","image":"https://assets.coingecko.com/coins/images/11085/large/Trust.png?1588062702","current_price":0.854583,"market_cap":356964576,"market_cap_rank":99,"fully_diluted_valuation":856749458,"total_volume":11450312,"high_24h":0.876321,"low_24h":0.823412,"price_change_24h":-0.01633647246691472,"price_change_percentage_24h":-1.87577,"market_cap_change_24h":-6239180.397245884,"market_cap_change_percentage_24h":-1.71782,"circulating_supply":416649900.0,"total_supply":1000000000.0,"max_supply":null,"ath":2.72,"ath_change_percentage":-68.44889,"ath_date":"2022-12-11T23:25:46.205Z","atl":0.00277641,"atl_change_percentage":30820.38439,"atl_date":"2020-06-09T09:15:06.983Z","roi":null,"last_updated":"2023-08-18T13:46:41.453Z"},{"id":"sui","symbol":"sui","name":"Sui","image":"https://assets.coingecko.com/coins/images/26375/large/sui_asset.jpeg?1683114182","current_price":0.479155,"market_cap":346229369,"market_cap_rank":100,"fully_diluted_valuation":4787713921,"total_volume":126556165,"high_24h":0.528231,"low_24h":0.462847,"price_change_24h":-0.04822603851554608,"price_change_percentage_24h":-9.14443,"market_cap_change_24h":-36830069.91528481,"market_cap_change_percentage_24h":-9.61471,"circulating_supply":723162190.461538,"total_supply":10000000000.0,"max_supply":10000000000.0,"ath":2.16,"ath_change_percentage":-77.8776,"ath_date":"2023-05-03T12:00:26.430Z","atl":0.462847,"atl_change_percentage":3.36038,"atl_date":"2023-08-17T22:50:06.690Z","roi":null,"last_updated":"2023-08-18T13:46:37.235Z"}]
